dask_lxplus/__init__.py
dask_lxplus/cluster.py
dask_lxplus/config.py
dask_lxplus/jobqueue-cern.yaml
dask_lxplus-0.3.3.dist-info/LICENSE.txt
dask_lxplus-0.3.3.dist-info/METADATA
dask_lxplus-0.3.3.dist-info/WHEEL
dask_lxplus-0.3.3.dist-info/top_level.txt
dask_lxplus-0.3.3.dist-info/RECORD
