Metadata-Version: 2.1
Name: dask-lxplus
Version: 0.3.3
Home-page: https://github.com/cernops/dask-lxplus
Author: Ben Jones
Author-email: b.jones@cern.ch
Classifier: Development Status :: 3 - Alpha
Classifier: Intended Audience :: Developers
Classifier: Intended Audience :: Science/Research
Classifier: Operating System :: OS Independent
Classifier: Programming Language :: Python :: 3
Classifier: Programming Language :: Python :: 3 :: Only
Classifier: Programming Language :: Python :: 3.6
Classifier: Programming Language :: Python :: 3.7
Classifier: Programming Language :: Python :: 3.8
Classifier: Topic :: System :: Distributed Computing
Requires-Python: >=3.6
License-File: LICENSE.txt
Requires-Dist: click (>=7.0)
Requires-Dist: click-didyoumean
Requires-Dist: cryptography
Requires-Dist: dask
Requires-Dist: dask-jobqueue (>=0.8.1)
Requires-Dist: humanize
Requires-Dist: psutil
Requires-Dist: pyyaml
Requires-Dist: watchdog
Requires-Dist: importlib-metadata (>=1.0) ; python_version < "3.9"
